autogluon.text-0.5.1-py3.7-nspkg.pth
autogluon/text/__init__.py
autogluon/text/version.py
autogluon/text/text_prediction/__init__.py
autogluon/text/text_prediction/config.py
autogluon/text/text_prediction/constants.py
autogluon/text/text_prediction/infer_types.py
autogluon/text/text_prediction/legacy_presets.py
autogluon/text/text_prediction/metrics.py
autogluon/text/text_prediction/mx_predictor.py
autogluon/text/text_prediction/predictor.py
autogluon/text/text_prediction/presets.py
autogluon/text/text_prediction/utils.py
autogluon/text/text_prediction/mx/__init__.py
autogluon/text/text_prediction/mx/models.py
autogluon/text/text_prediction/mx/modules.py
autogluon/text/text_prediction/mx/preprocessing.py
autogluon/text/text_prediction/mx/utils.py
autogluon.text-0.5.1.dist-info/LICENSE
autogluon.text-0.5.1.dist-info/METADATA
autogluon.text-0.5.1.dist-info/NOTICE
autogluon.text-0.5.1.dist-info/WHEEL
autogluon.text-0.5.1.dist-info/namespace_packages.txt
autogluon.text-0.5.1.dist-info/top_level.txt
autogluon.text-0.5.1.dist-info/zip-safe
autogluon.text-0.5.1.dist-info/RECORD
