Metadata-Version: 2.1
Name: autogluon.text
Version: 0.5.1
Summary: AutoML for Image, Text, and Tabular Data
Home-page: https://github.com/awslabs/autogluon
Author: AutoGluon Community
License: Apache-2.0
Project-URL: Documentation, https://auto.gluon.ai
Project-URL: Bug Reports, https://github.com/awslabs/autogluon/issues
Project-URL: Source, https://github.com/awslabs/autogluon/
Project-URL: Contribute!, https://github.com/awslabs/autogluon/blob/master/CONTRIBUTING.md
Platform: UNKNOWN
Classifier: Development Status :: 4 - Beta
Classifier: Intended Audience :: Education
Classifier: Intended Audience :: Developers
Classifier: Intended Audience :: Science/Research
Classifier: Intended Audience :: Customer Service
Classifier: Intended Audience :: Financial and Insurance Industry
Classifier: Intended Audience :: Healthcare Industry
Classifier: Intended Audience :: Telecommunications Industry
Classifier: License :: OSI Approved :: Apache Software License
Classifier: Operating System :: MacOS
Classifier: Operating System :: Microsoft :: Windows
Classifier: Operating System :: POSIX
Classifier: Operating System :: Unix
Classifier: Programming Language :: Python :: 3
Classifier: Programming Language :: Python :: 3.7
Classifier: Programming Language :: Python :: 3.8
Classifier: Programming Language :: Python :: 3.9
Classifier: Topic :: Software Development
Classifier: Topic :: Scientific/Engineering :: Artificial Intelligence
Classifier: Topic :: Scientific/Engineering :: Information Analysis
Classifier: Topic :: Scientific/Engineering :: Image Recognition
Requires-Python: >=3.7, <3.10
Requires-Dist: autogluon.multimodal (==0.5.1)
Requires-Dist: autogluon-contrib-nlp (==0.0.1b20220208)
Provides-Extra: tests
Requires-Dist: black (>=22.3,~=22.0) ; extra == 'tests'
